audiodag/__init__.py
audiodag/common/__init__.py
audiodag/common/repr_id.py
audiodag/signal/__init__.py
audiodag/signal/components/__init__.py
audiodag/signal/components/component.py
audiodag/signal/components/noise_component.py
audiodag/signal/components/sine_component.py
audiodag/signal/digital/__init__.py
audiodag/signal/digital/conversion.py
audiodag/signal/digital/digital_siginal.py
audiodag/signal/envelopes/__init__.py
audiodag/signal/envelopes/envelope.py
audiodag/signal/envelopes/templates.py
audiodag/stim/__init__.py
audiodag/stim/templates_basic.py
audiodag/stim/templates_complex.py
tests/__init__.py
tests/integration/__init__.py
tests/integration/signal/__init__.py
tests/integration/signal/components/__init__.py
tests/integration/signal/components/test_compound_component.py
tests/unit/__init__.py
tests/unit/signal/__init__.py
tests/unit/signal/components/__init__.py
tests/unit/signal/components/test_component.py
tests/unit/signal/components/test_compound_component.py
tests/unit/signal/components/test_noise_component.py
tests/unit/signal/components/test_sine_component.py
tests/unit/signal/digital/__init__.py
tests/unit/signal/digital/test_digital_signal.py
tests/unit/signal/envelopes/__init__.py
tests/unit/signal/envelopes/test_envelopes.py
AudioDAG-0.0.19.dist-info/LICENSE
AudioDAG-0.0.19.dist-info/METADATA
AudioDAG-0.0.19.dist-info/WHEEL
AudioDAG-0.0.19.dist-info/top_level.txt
AudioDAG-0.0.19.dist-info/RECORD
