Metadata-Version: 2.1
Name: AudioDAG
Version: 0.0.19
Summary: UNKNOWN
Home-page: https://github.com/garethjns/AudioDAG
Author: Gareth Jones
Author-email: 
License: UNKNOWN
Platform: UNKNOWN
Classifier: Programming Language :: Python :: 3
Classifier: Operating System :: OS Independent
Requires-Python: >=3.6
Requires-Dist: numpy
Requires-Dist: dataclasses
Requires-Dist: matplotlib
